HLProp/HLP.py
HLProp/HLP_lookup_table.pt
HLProp/__init__.py
hlprop-0.0.1.dist-info/METADATA
hlprop-0.0.1.dist-info/WHEEL
hlprop-0.0.1.dist-info/licenses/LICENSE
hlprop-0.0.1.dist-info/RECORD
